README.rst
setup.py
swjsq/__init__.py
swjsq/_compat.py
swjsq/cli.py
swjsq/core.py
swjsq/exceptions.py
swjsq/http.py
swjsq/rsa.py
swjsq/utils.py
swjsq.egg-info/PKG-INFO
swjsq.egg-info/SOURCES.txt
swjsq.egg-info/dependency_links.txt
swjsq.egg-info/entry_points.txt
swjsq.egg-info/top_level.txt