Metadata-Version: 1.1
Name: swjsq
Version: 0.5
Summary: A command line client for Xunlei SWJSQ (aka. 迅雷快鸟)
Home-page: https://github.com/timothyqiu/python-swjsq
Author: Timothy Qiu
Author-email: timothyqiu32@gmail.com
License: MIT
Download-URL: https://github.com/timothyqiu/python-swjsq/archive/0.5.tar.gz
Keywords: xunlei
Platform: UNKNOWN
Classifier: Development Status :: 4 - Beta
Classifier: Environment :: Console
Classifier: Intended Audience :: Developers
Classifier: Intended Audience :: End Users/Desktop
Classifier: License :: OSI Approved :: MIT License
Classifier: Operating System :: OS Independent
Classifier: Topic :: Internet
Classifier: Topic :: Utilities
